fh_saas/__init__.py
fh_saas/_modidx.py
fh_saas/core.py
fh_saas/db_host.py
fh_saas/db_tenant.py
fh_saas/utils_api.py
fh_saas/utils_auth.py
fh_saas/utils_bgtsk.py
fh_saas/utils_blog.py
fh_saas/utils_db.py
fh_saas/utils_email.py
fh_saas/utils_graphql.py
fh_saas/utils_log.py
fh_saas/utils_migrate.py
fh_saas/utils_polars_mapper.py
fh_saas/utils_seo.py
fh_saas/utils_sql.py
fh_saas/utils_stripe.py
fh_saas/utils_webhook.py
fh_saas/utils_workflow.py
fh_saas-0.9.9.dist-info/licenses/LICENSE
fh_saas-0.9.9.dist-info/METADATA
fh_saas-0.9.9.dist-info/WHEEL
fh_saas-0.9.9.dist-info/entry_points.txt
fh_saas-0.9.9.dist-info/top_level.txt
fh_saas-0.9.9.dist-info/RECORD
