Metadata-Version: 2.4
Name: fh-saas
Version: 0.9.9
Summary: Production-ready multi-tenant SaaS toolkit for FastHTML applications with authentication, billing, and integrations
Home-page: https://github.com/abhisheksreesaila/fh-saas
Author: abhishek sreesaila
Author-email: abhishek.sreesaila@gmail.com
License: Apache Software License 2.0
Keywords: nbdev jupyter notebook python fasthtml saas multi-tenant oauth authentication
Classifier: Development Status :: 4 - Beta
Classifier: Intended Audience :: Developers
Classifier: Natural Language :: English
Classifier: Programming Language :: Python :: 3.9
Classifier: Programming Language :: Python :: 3.10
Classifier: Programming Language :: Python :: 3.11
Classifier: Programming Language :: Python :: 3.12
Classifier: License :: OSI Approved :: Apache Software License
Requires-Python: >=3.9
License-File: LICENSE
Requires-Dist: httpx>=0.25.0
Requires-Dist: tenacity>=8.2.0
Requires-Dist: polars>=0.20.0
Requires-Dist: Markdown>=3.4.0
Requires-Dist: python-frontmatter>=1.1.0
Requires-Dist: pygments>=2.17.0
Requires-Dist: fastsql
Requires-Dist: python-fasthtml
Requires-Dist: starlette
Requires-Dist: python-dotenv
Requires-Dist: sqlalchemy
Requires-Dist: fastcore
Requires-Dist: stripe
Requires-Dist: faststripe
Provides-Extra: dev
Dynamic: author
Dynamic: author-email
Dynamic: classifier
Dynamic: description
Dynamic: description-content-type
Dynamic: home-page
Dynamic: keywords
Dynamic: license
Dynamic: license-file
Dynamic: provides-extra
Dynamic: requires-dist
Dynamic: requires-python
Dynamic: summary
